long_short_transformer/__init__.py
long_short_transformer/autoregressive_wrapper.py
long_short_transformer/long_short_transformer.py
long_short_transformer-0.0.5.dist-info/LICENSE
long_short_transformer-0.0.5.dist-info/METADATA
long_short_transformer-0.0.5.dist-info/WHEEL
long_short_transformer-0.0.5.dist-info/top_level.txt
long_short_transformer-0.0.5.dist-info/RECORD
