Metadata-Version: 2.1
Name: long-short-transformer
Version: 0.0.5
Summary: Long Short Transformer - Pytorch
Home-page: https://github.com/lucidrains/long-short-transformer
Author: Phil Wang
Author-email: lucidrains@gmail.com
License: MIT
Keywords: artificial intelligence,deep learning,transformers,efficient attention
Platform: UNKNOWN
Classifier: Development Status :: 4 - Beta
Classifier: Intended Audience :: Developers
Classifier: Topic :: Scientific/Engineering :: Artificial Intelligence
Classifier: License :: OSI Approved :: MIT License
Classifier: Programming Language :: Python :: 3.6
License-File: LICENSE
Requires-Dist: einops (>=0.3)
Requires-Dist: rotary-embedding-torch
Requires-Dist: torch (>=1.6)
